otsubsetinverse/__init__.py
otsubsetinverse/libotsubsetinverse.dll
otsubsetinverse/otsubsetinverse.py
otsubsetinverse/_otsubsetinverse.pyd
otsubsetinverse-1.10.dist-info/METADATA
otsubsetinverse-1.10.dist-info/WHEEL
otsubsetinverse-1.10.dist-info/RECORD
